wagtail_notes/__init__.py
wagtail_notes/wagtail_hooks.py
wagtail_notes/locale/fr/LC_MESSAGES/django.mo
wagtail_notes/locale/fr/LC_MESSAGES/django.po
wagtail_notes/static/js/note.js
wagtail_notes/templates/wagtailadmin/widgets/draftail_rich_text_area.html
wagtail_notes-1.0.3.dist-info/licenses/LICENSE
wagtail_notes-1.0.3.dist-info/METADATA
wagtail_notes-1.0.3.dist-info/WHEEL
wagtail_notes-1.0.3.dist-info/top_level.txt
wagtail_notes-1.0.3.dist-info/RECORD
