Metadata-Version: 2.4
Name: wagtail-notes
Version: 1.0.3
Summary: Adds anchor links and related backlinks to the Wagtail editor (Draftail). Useful for footnotes and more!
Author-email: Bertrand Bordage <bordage.bertrand@gmail.com>
License: BSD-3-Clause
Project-URL: Homepage, https://github.com/noripyt/wagtail-notes
Project-URL: Issues, https://github.com/noripyt/wagtail-notes/issues
Classifier: Programming Language :: Python :: 3
Classifier: Operating System :: OS Independent
Requires-Python: >=3.8
License-File: LICENSE
Requires-Dist: wagtail-font-awesome-svg
Dynamic: license-file
